README.md
setup.py
ezmaps/__init__.py
ezmaps/__main__.py
ezmaps/ezmap.py
ezmaps/markers.py
ezmaps/overpass.py
ezmaps/util.py
ezmaps.egg-info/PKG-INFO
ezmaps.egg-info/SOURCES.txt
ezmaps.egg-info/dependency_links.txt
ezmaps.egg-info/entry_points.txt
ezmaps.egg-info/requires.txt
ezmaps.egg-info/top_level.txt