Metadata-Version: 2.1
Name: ezmaps
Version: 1.1.0
Summary: Generate Beautiful Maps
Home-page: https://github.com/c00kie17/ezmaps
Author: c00kie17
Author-email: anshul1708@gmail.com
License: UNKNOWN
Platform: UNKNOWN
Classifier: Programming Language :: Python :: 3
Classifier: License :: OSI Approved :: MIT License
Classifier: Operating System :: OS Independent
